setup.py
jerrypackage.egg-info/PKG-INFO
jerrypackage.egg-info/SOURCES.txt
jerrypackage.egg-info/dependency_links.txt
jerrypackage.egg-info/entry_points.txt
jerrypackage.egg-info/requires.txt
jerrypackage.egg-info/top_level.txt
jerrypackage/omtv/Episode.py
jerrypackage/omtv/Season.py
jerrypackage/omtv/TV.py
jerrypackage/omtv/msj1_com.py
jerrypackage/tools/__init__.py
jerrypackage/tools/chinanumber.py
jerrypackage/tools/chinanumbertest.py
jerrypackage/tools/romannumber.py
jerrypackage/tools/romannumbertest.py
jerrypackage/tools/simple.py
jerrypackage/xzb/verification_code.py
jerrypackage/xzb/xzb_api.py