Metadata-Version: 1.0
Name: jerrypackage
Version: 0.0.9
Summary: Tools for daily use
Home-page: https://www.zhihu.com/people/jerrychen-57/activities
Author: jerrychy
Author-email: jerrychen@ustc.edu
License: UNKNOWN
Platform: UNKNOWN
